barcode_server/__init__.py
barcode_server/barcode.py
barcode_server/cli.py
barcode_server/config.py
barcode_server/const.py
barcode_server/keyevent_reader.py
barcode_server/notifier/__init__.py
barcode_server/notifier/http.py
barcode_server/notifier/mqtt.py
barcode_server/notifier/ws.py
barcode_server/stats.py
barcode_server/util.py
barcode_server/webserver.py
barcode_server-2.5.0.dist-info/LICENSE
barcode_server-2.5.0.dist-info/METADATA
barcode_server-2.5.0.dist-info/WHEEL
barcode_server-2.5.0.dist-info/entry_points.txt
barcode_server-2.5.0.dist-info/RECORD
