Metadata-Version: 2.3
Name: barcode-server
Version: 2.5.0
Summary: A simple daemon to expose USB Barcode Scanner data to other services using Websockets, Webhooks or MQTT.
License: AGPL-3.0-or-later
Keywords: barcode,asyncio,qrcode,http,mqtt,server,websocket,websocket
Author: Markus Ressel
Author-email: mail@markusressel.de
Requires-Python: >=3.13,<4.0
Classifier: Development Status :: 5 - Production/Stable
Classifier: License :: OSI Approved :: GNU Affero General Public License v3 or later (AGPLv3+)
Classifier: Programming Language :: Python :: 3
Classifier: Programming Language :: Python :: 3.13
Classifier: Programming Language :: Python :: 3 :: Only
Classifier: Programming Language :: Python :: 3.7
Classifier: Programming Language :: Python :: 3.8
Classifier: Programming Language :: Python :: 3.9
Requires-Dist: aiohttp
Requires-Dist: aiomqtt
Requires-Dist: click
Requires-Dist: container-app-conf (>=5.0.0)
Requires-Dist: evdev
Requires-Dist: orjson
Requires-Dist: prometheus-client
Requires-Dist: prometheus_async
Requires-Dist: ruamel-yaml-clib (==0.2.12)
Project-URL: Homepage, https://github.com/markusressel/barcode-server
Project-URL: Repository, https://github.com/markusressel/barcode-server
